{
    "lighthouse": {
        "slot": 3839976,
        "network": "holesky",
        "client": "lighthouse",
        "timestamp": "2025-03-14 19:55:13.050000",
        "status": "produced",
        "hash": "0xcd087f21a93aefcbd4f36640c4d3ea8670db1c161d43f7740eb6271836b937b9",
        "parent_hash": "0x57712b3876c1168e82236037dad25afcd6aa25703ee90acd43285445c12b98c3",
        "timestamp_seconds": 1741982113050.0,
        "seconds_in_slot": 2.05
    },
    "lodestar": {
        "slot": 3839976,
        "network": "holesky",
        "client": "lodestar",
        "timestamp": "2025-03-14 19:55:13.072000",
        "status": "produced",
        "hash": "0xcd087f21a93aefcbd4f36640c4d3ea8670db1c161d43f7740eb6271836b937b9",
        "parent_hash": "0x57712b3876c1168e82236037dad25afcd6aa25703ee90acd43285445c12b98c3",
        "timestamp_seconds": 1741982113072.0,
        "seconds_in_slot": 2.072
    },
    "nimbus": {
        "slot": 3839976,
        "network": "holesky",
        "client": "nimbus",
        "timestamp": "2025-03-14 19:55:12.979000",
        "status": "produced",
        "hash": "0xcd087f21a93aefcbd4f36640c4d3ea8670db1c161d43f7740eb6271836b937b9",
        "parent_hash": "0x57712b3876c1168e82236037dad25afcd6aa25703ee90acd43285445c12b98c3",
        "timestamp_seconds": 1741982112979.0,
        "seconds_in_slot": 1.979
    },
    "prysm": {
        "slot": 3839976,
        "network": "holesky",
        "client": "prysm",
        "timestamp": "2025-03-14 19:55:13.017000",
        "status": "produced",
        "hash": "0xcd087f21a93aefcbd4f36640c4d3ea8670db1c161d43f7740eb6271836b937b9",
        "parent_hash": "0x57712b3876c1168e82236037dad25afcd6aa25703ee90acd43285445c12b98c3",
        "timestamp_seconds": 1741982113017.0,
        "seconds_in_slot": 2.017
    },
    "teku": {
        "slot": 3839976,
        "network": "holesky",
        "client": "teku",
        "timestamp": "2025-03-14 19:55:13.068000",
        "status": "produced",
        "hash": "0xcd087f21a93aefcbd4f36640c4d3ea8670db1c161d43f7740eb6271836b937b9",
        "parent_hash": "0x57712b3876c1168e82236037dad25afcd6aa25703ee90acd43285445c12b98c3",
        "timestamp_seconds": 1741982113068.0,
        "seconds_in_slot": 2.068
    }
}