{
    "lighthouse": {
        "slot": 3839773,
        "network": "holesky",
        "client": "lighthouse",
        "timestamp": "2025-03-14 19:14:41.121000",
        "status": "produced",
        "hash": "0x1a2aafe7312dc97d2d0cf8b768e8a22021bfdd8a93b064660ed2b4299d3a6ecd",
        "parent_hash": "0xfc4cae488a56552cba552dbf304e68b36f3d2c3efae19f9ef5a5b118a71ad57d",
        "timestamp_seconds": 1741979681121.0,
        "seconds_in_slot": 6.121
    },
    "lodestar": {
        "slot": 3839773,
        "network": "holesky",
        "client": "lodestar",
        "timestamp": "2025-03-14 19:14:40.904000",
        "status": "produced",
        "hash": "0x1a2aafe7312dc97d2d0cf8b768e8a22021bfdd8a93b064660ed2b4299d3a6ecd",
        "parent_hash": "0xfc4cae488a56552cba552dbf304e68b36f3d2c3efae19f9ef5a5b118a71ad57d",
        "timestamp_seconds": 1741979680904.0,
        "seconds_in_slot": 5.904
    },
    "nimbus": {
        "slot": 3839773,
        "network": "holesky",
        "client": "nimbus",
        "timestamp": "2025-03-14 19:14:40.819000",
        "status": "produced",
        "hash": "0x1a2aafe7312dc97d2d0cf8b768e8a22021bfdd8a93b064660ed2b4299d3a6ecd",
        "parent_hash": "0xfc4cae488a56552cba552dbf304e68b36f3d2c3efae19f9ef5a5b118a71ad57d",
        "timestamp_seconds": 1741979680819.0,
        "seconds_in_slot": 5.819
    },
    "prysm": {
        "slot": 3839773,
        "network": "holesky",
        "client": "prysm",
        "timestamp": "2025-03-14 19:14:40.827000",
        "status": "produced",
        "hash": "0x1a2aafe7312dc97d2d0cf8b768e8a22021bfdd8a93b064660ed2b4299d3a6ecd",
        "parent_hash": "0xfc4cae488a56552cba552dbf304e68b36f3d2c3efae19f9ef5a5b118a71ad57d",
        "timestamp_seconds": 1741979680827.0,
        "seconds_in_slot": 5.827
    },
    "teku": {
        "slot": 3839773,
        "network": "holesky",
        "client": "teku",
        "timestamp": "2025-03-14 19:14:41.099000",
        "status": "produced",
        "hash": "0x1a2aafe7312dc97d2d0cf8b768e8a22021bfdd8a93b064660ed2b4299d3a6ecd",
        "parent_hash": "0xfc4cae488a56552cba552dbf304e68b36f3d2c3efae19f9ef5a5b118a71ad57d",
        "timestamp_seconds": 1741979681099.0,
        "seconds_in_slot": 6.099
    }
}